Workbook

Sheet Computation Sheet
A3: Employee information | G3: Salary information | S3: Cost to Company
A5: Sr.No | B5: E-Code | C5: Name | D5: Days in Month | E5: Payable days | G5: Basic | H5: HRA | I5: Special All | J5: OT | K5: Incentive | L5: Gross Salary | M5: EPF | N5: ESI | O5: TDS | P5: Pro Tax | Q5: Net Salary | S5: PFCO | T5: PF Exp | U5: ESI Co | V5: Gratuity | W5: Bonus | X5: CTC | Z5: Remark
A6: 1 | B6: D49404 | C6: =+VLOOKUP(B6,Structure!$B$3:$C$12,2,0) -> Argha Roy | D6: 31 | E6: 31 | G6: =VLOOKUP(B6,Structure!$B$3:$D$12,3,0)/D6*E6 -> 14300 | H6: =VLOOKUP(B6,Structure!$B$3:$E$12,4,0)/D6*E6 -> 7104 | I6: =VLOOKUP(B6,Structure!$B$3:$F$12,5,0)/D6*E6 -> 0 | J6: 0 | K6: 0 | L6: =+SUM(G6:K6) -> 21404 | M6: =IF(G6<=15000,G6*12%,15000*12%) -> 1716 | N6: =IF(L6<=21000,L6*0.75%,0) -> 0 | O6: =+VLOOKUP(B6,TDS!$B$9:$E$18,4,0) -> 0 | P6: 0 | Q6: =+L6-M6-N6-O6-P6 -> 19688 | S6: =M6 -> 1716 | T6: =IF(G6<=15000,G6*1/100,150) -> 143 | U6: =N6/0.75*3.25 -> 0 | V6: =+G6*4.81% -> 687.83 | W6: =+VLOOKUP(B6,Bonus!$C$5:$K$14,9,0) -> 0 | X6: =+L6+S6+T6+U6+V6+W6 -> 23950.83
A7: =+A6+1 -> 2 | B7: D49405 | C7: =+VLOOKUP(B7,Structure!$B$3:$C$12,2,0) -> Ashish Tiwari | D7: 31 | E7: 31 | G7: =VLOOKUP(B7,Structure!$B$3:$D$12,3,0)/D7*E7 -> 17000 | H7: =VLOOKUP(B7,Structure!$B$3:$E$12,4,0)/D7*E7 -> 8500 | I7: =VLOOKUP(B7,Structure!$B$3:$F$12,5,0)/D7*E7 -> 5633 | J7: 0 | K7: 0 | L7: =+SUM(G7:K7) -> 31133 | M7: =IF(G7<=15000,G7*12%,15000*12%) -> 1800 | N7: =IF(L7<=21000,L7*0.75%,0) -> 0 | O7: =+VLOOKUP(B7,TDS!$B$9:$E$18,4,0) -> 0 | P7: 0 | Q7: =+L7-M7-N7-O7-P7 -> 29333 | S7: =M7 -> 1800 | T7: =IF(G7<=15000,G7*1/100,150) -> 150 | U7: =N7/0.75*3.25 -> 0 | V7: =+G7*4.81% -> 817.7 | W7: =+VLOOKUP(B7,Bonus!$C$5:$K$14,9,0) -> 0 | X7: =+L7+S7+T7+U7+V7+W7 -> 33900.7
A8: =+A7+1 -> 3 | B8: D49408 | C8: =+VLOOKUP(B8,Structure!$B$3:$C$12,2,0) -> Aslam Sabri | D8: 31 | E8: 31 | G8: =VLOOKUP(B8,Structure!$B$3:$D$12,3,0)/D8*E8 -> 80000 | H8: =VLOOKUP(B8,Structure!$B$3:$E$12,4,0)/D8*E8 -> 37000 | I8: =VLOOKUP(B8,Structure!$B$3:$F$12,5,0)/D8*E8 -> 57075 | J8: 0 | K8: 0 | L8: =+SUM(G8:K8) -> 174075 | M8: =IF(G8<=15000,G8*12%,15000*12%) -> 1800 | N8: =IF(L8<=21000,L8*0.75%,0) -> 0 | O8: =+VLOOKUP(B8,TDS!$B$9:$E$18,4,0) -> 1800 | P8: 0 | Q8: =+L8-M8-N8-O8-P8 -> 170475 | S8: =M8 -> 1800 | T8: =IF(G8<=15000,G8*1/100,150) -> 150 | U8: =N8/0.75*3.25 -> 0 | V8: =+G8*4.81% -> 3848 | W8: =+VLOOKUP(B8,Bonus!$C$5:$K$14,9,0) -> 0 | X8: =+L8+S8+T8+U8+V8+W8 -> 179873
A9: =+A8+1 -> 4 | B9: D49409 | C9: =+VLOOKUP(B9,Structure!$B$3:$C$12,2,0) -> Avik Das | D9: 31 | E9: 31 | G9: =VLOOKUP(B9,Structure!$B$3:$D$12,3,0)/D9*E9 -> 13500 | H9: =VLOOKUP(B9,Structure!$B$3:$E$12,4,0)/D9*E9 -> 6284 | I9: =VLOOKUP(B9,Structure!$B$3:$F$12,5,0)/D9*E9 -> 0 | J9: 0 | K9: 0 | L9: =+SUM(G9:K9) -> 19784 | M9: =IF(G9<=15000,G9*12%,15000*12%) -> 1620 | N9: =IF(L9<=21000,L9*0.75%,0) -> 148.38 | O9: =+VLOOKUP(B9,TDS!$B$9:$E$18,4,0) -> 0 | P9: 0 | Q9: =+L9-M9-N9-O9-P9 -> 18015.62 | S9: =M9 -> 1620 | T9: =IF(G9<=15000,G9*1/100,150) -> 135 | U9: =N9/0.75*3.25 -> 642.98 | V9: =+G9*4.81% -> 649.35 | W9: =+VLOOKUP(B9,Bonus!$C$5:$K$14,9,0) -> 1493.0692 | X9: =+L9+S9+T9+U9+V9+W9 -> 24324.399
A10: =+A9+1 -> 5 | B10: D49410 | C10: =+VLOOKUP(B10,Structure!$B$3:$C$12,2,0) -> Avtar Singh | D10: 31 | E10: 31 | G10: =VLOOKUP(B10,Structure!$B$3:$D$12,3,0)/D10*E10 -> 13500 | H10: =VLOOKUP(B10,Structure!$B$3:$E$12,4,0)/D10*E10 -> 6284 | I10: =VLOOKUP(B10,Structure!$B$3:$F$12,5,0)/D10*E10 -> 0 | J10: 0 | K10: 0 | L10: =+SUM(G10:K10) -> 19784 | M10: =IF(G10<=15000,G10*12%,15000*12%) -> 1620 | N10: =IF(L10<=21000,L10*0.75%,0) -> 148.38 | O10: =+VLOOKUP(B10,TDS!$B$9:$E$18,4,0) -> 0 | P10: 0 | Q10: =+L10-M10-N10-O10-P10 -> 18015.62 | S10: =M10 -> 1620 | T10: =IF(G10<=15000,G10*1/100,150) -> 135 | U10: =N10/0.75*3.25 -> 642.98 | V10: =+G10*4.81% -> 649.35 | W10: =+VLOOKUP(B10,Bonus!$C$5:$K$14,9,0) -> 1356.4572 | X10: =+L10+S10+T10+U10+V10+W10 -> 24187.787
A11: =+A10+1 -> 6 | B11: D49411 | C11: =+VLOOKUP(B11,Structure!$B$3:$C$12,2,0) -> Brotin Ghosh | D11: 31 | E11: 31 | G11: =VLOOKUP(B11,Structure!$B$3:$D$12,3,0)/D11*E11 -> 13500 | H11: =VLOOKUP(B11,Structure!$B$3:$E$12,4,0)/D11*E11 -> 6284 | I11: =VLOOKUP(B11,Structure!$B$3:$F$12,5,0)/D11*E11 -> 0 | J11: 0 | K11: 0 | L11: =+SUM(G11:K11) -> 19784 | M11: =IF(G11<=15000,G11*12%,15000*12%) -> 1620 | N11: =IF(L11<=21000,L11*0.75%,0) -> 148.38 | O11: =+VLOOKUP(B11,TDS!$B$9:$E$18,4,0) -> 0 | P11: 0 | Q11: =+L11-M11-N11-O11-P11 -> 18015.62 | S11: =M11 -> 1620 | T11: =IF(G11<=15000,G11*1/100,150) -> 135 | U11: =N11/0.75*3.25 -> 642.98 | V11: =+G11*4.81% -> 649.35 | W11: =+VLOOKUP(B11,Bonus!$C$5:$K$14,9,0) -> 1233.3398 | X11: =+L11+S11+T11+U11+V11+W11 -> 24064.67
A12: =+A11+1 -> 7 | B12: D49415 | C12: =+VLOOKUP(B12,Structure!$B$3:$C$12,2,0) -> Devesh Yadav | D12: 31 | E12: 31 | G12: =VLOOKUP(B12,Structure!$B$3:$D$12,3,0)/D12*E12 -> 25000 | H12: =VLOOKUP(B12,Structure!$B$3:$E$12,4,0)/D12*E12 -> 12500 | I12: =VLOOKUP(B12,Structure!$B$3:$F$12,5,0)/D12*E12 -> 15929 | J12: 0 | K12: 0 | L12: =+SUM(G12:K12) -> 53429 | M12: =IF(G12<=15000,G12*12%,15000*12%) -> 1800 | N12: =IF(L12<=21000,L12*0.75%,0) -> 0 | O12: =+VLOOKUP(B12,TDS!$B$9:$E$18,4,0) -> 1200 | P12: 0 | Q12: =+L12-M12-N12-O12-P12 -> 50429 | S12: =M12 -> 1800 | T12: =IF(G12<=15000,G12*1/100,150) -> 150 | U12: =N12/0.75*3.25 -> 0 | V12: =+G12*4.81% -> 1202.5 | W12: =+VLOOKUP(B12,Bonus!$C$5:$K$14,9,0) -> 0 | X12: =+L12+S12+T12+U12+V12+W12 -> 56581.5
A13: =+A12+1 -> 8 | B13: D49416 | C13: =+VLOOKUP(B13,Structure!$B$3:$C$12,2,0) -> Dinesh Kumar | D13: 31 | E13: 31 | G13: =VLOOKUP(B13,Structure!$B$3:$D$12,3,0)/D13*E13 -> 26000 | H13: =VLOOKUP(B13,Structure!$B$3:$E$12,4,0)/D13*E13 -> 13000 | I13: =VLOOKUP(B13,Structure!$B$3:$F$12,5,0)/D13*E13 -> 7720 | J13: 0 | K13: 0 | L13: =+SUM(G13:K13) -> 46720 | M13: =IF(G13<=15000,G13*12%,15000*12%) -> 1800 | N13: =IF(L13<=21000,L13*0.75%,0) -> 0 | O13: =+VLOOKUP(B13,TDS!$B$9:$E$18,4,0) -> 600 | P13: 0 | Q13: =+L13-M13-N13-O13-P13 -> 44320 | S13: =M13 -> 1800 | T13: =IF(G13<=15000,G13*1/100,150) -> 150 | U13: =N13/0.75*3.25 -> 0 | V13: =+G13*4.81% -> 1250.6 | W13: =+VLOOKUP(B13,Bonus!$C$5:$K$14,9,0) -> 0 | X13: =+L13+S13+T13+U13+V13+W13 -> 49920.6
A14: =+A13+1 -> 9 | B14: D49418 | C14: =+VLOOKUP(B14,Structure!$B$3:$C$12,2,0) -> Dushyant Yadav | D14: 31 | E14: 31 | G14: =VLOOKUP(B14,Structure!$B$3:$D$12,3,0)/D14*E14 -> 35000 | H14: =VLOOKUP(B14,Structure!$B$3:$E$12,4,0)/D14*E14 -> 17500 | I14: =VLOOKUP(B14,Structure!$B$3:$F$12,5,0)/D14*E14 -> 1587 | J14: 0 | K14: 0 | L14: =+SUM(G14:K14) -> 54087 | M14: =IF(G14<=15000,G14*12%,15000*12%) -> 1800 | N14: =IF(L14<=21000,L14*0.75%,0) -> 0 | O14: =+VLOOKUP(B14,TDS!$B$9:$E$18,4,0) -> 1250 | P14: 0 | Q14: =+L14-M14-N14-O14-P14 -> 51037 | S14: =M14 -> 1800 | T14: =IF(G14<=15000,G14*1/100,150) -> 150 | U14: =N14/0.75*3.25 -> 0 | V14: =+G14*4.81% -> 1683.5 | W14: =+VLOOKUP(B14,Bonus!$C$5:$K$14,9,0) -> 0 | X14: =+L14+S14+T14+U14+V14+W14 -> 57720.5
A15: =+A14+1 -> 10 | B15: D49421 | C15: =+VLOOKUP(B15,Structure!$B$3:$C$12,2,0) -> Indrajit Das | D15: 31 | E15: 31 | G15: =VLOOKUP(B15,Structure!$B$3:$D$12,3,0)/D15*E15 -> 32000 | H15: =VLOOKUP(B15,Structure!$B$3:$E$12,4,0)/D15*E15 -> 16000 | I15: =VLOOKUP(B15,Structure!$B$3:$F$12,5,0)/D15*E15 -> 12000 | J15: 0 | K15: 0 | L15: =+SUM(G15:K15) -> 60000 | M15: =IF(G15<=15000,G15*12%,15000*12%) -> 1800 | N15: =IF(L15<=21000,L15*0.75%,0) -> 0 | O15: =+VLOOKUP(B15,TDS!$B$9:$E$18,4,0) -> 1400 | P15: 0 | Q15: =+L15-M15-N15-O15-P15 -> 56800 | S15: =M15 -> 1800 | T15: =IF(G15<=15000,G15*1/100,150) -> 150 | U15: =N15/0.75*3.25 -> 0 | V15: =+G15*4.81% -> 1539.2 | W15: =+VLOOKUP(B15,Bonus!$C$5:$K$14,9,0) -> 0 | X15: =+L15+S15+T15+U15+V15+W15 -> 63489.2

Sheet Bonus
B4: Sr.No | C4: E-Code | D4: Name | E4: State | F4: Nature | G4: Gross salary | H4: Eligibility | I4: Minimum Wages | J4: Ceiling | K4: Bonus Amount
B5: 1 | C5: D49404 | D5: Argha Roy | E5: Delhi | F5: Unskilled | G5: =+VLOOKUP(C5,'Computation Sheet'!B5:L15,11,0) -> 21404 | H5: =IF(G5<=21000,"Yes","No") -> No | I5: =VLOOKUP(F5,$B$18:$H$23,7,0)/'Computation Sheet'!D6*'Computation Sheet'!E6 -> 14806 | J5: 7000 | K5: =IF(H5="Yes",MAX(I5,J5)*8.33%,0) -> 0
B6: 2 | C6: D49405 | D6: Ashish Tiwari | E6: Delhi | F6: Unskilled | G6: =+VLOOKUP(C6,'Computation Sheet'!B6:L16,11,0) -> 31133 | H6: =IF(G6<=21000,"Yes","No") -> No | I6: =VLOOKUP(F6,$B$18:$H$23,7,0)/'Computation Sheet'!D7*'Computation Sheet'!E7 -> 14806 | J6: 7000 | K6: =IF(H6="Yes",MAX(I6,J6)*8.33%,0) -> 0
B7: 3 | C7: D49408 | D7: Aslam Sabri | E7: Delhi | F7: Unskilled | G7: =+VLOOKUP(C7,'Computation Sheet'!B7:L17,11,0) -> 174075 | H7: =IF(G7<=21000,"Yes","No") -> No | I7: =VLOOKUP(F7,$B$18:$H$23,7,0)/'Computation Sheet'!D8*'Computation Sheet'!E8 -> 14806 | J7: 7000 | K7: =IF(H7="Yes",MAX(I7,J7)*8.33%,0) -> 0
B8: 4 | C8: D49409 | D8: Avik Das | E8: Delhi | F8: Skilled | G8: =+VLOOKUP(C8,'Computation Sheet'!B8:L18,11,0) -> 19784 | H8: =IF(G8<=21000,"Yes","No") -> Yes | I8: =VLOOKUP(F8,$B$18:$H$23,7,0)/'Computation Sheet'!D9*'Computation Sheet'!E9 -> 17924 | J8: 7000 | K8: =IF(H8="Yes",MAX(I8,J8)*8.33%,0) -> 1493.0692
B9: 5 | C9: D49410 | D9: Avtar Singh | E9: Delhi | F9: Semi-Skilled | G9: =+VLOOKUP(C9,'Computation Sheet'!B9:L19,11,0) -> 19784 | H9: =IF(G9<=21000,"Yes","No") -> Yes | I9: =VLOOKUP(F9,$B$18:$H$23,7,0)/'Computation Sheet'!D10*'Computation Sheet'!E10 -> 16284 | J9: 7000 | K9: =IF(H9="Yes",MAX(I9,J9)*8.33%,0) -> 1356.4572
B10: 6 | C10: D49411 | D10: Brotin Ghosh | E10: Delhi | F10: Unskilled | G10: =+VLOOKUP(C10,'Computation Sheet'!B10:L20,11,0) -> 19784 | H10: =IF(G10<=21000,"Yes","No") -> Yes | I10: =VLOOKUP(F10,$B$18:$H$23,7,0)/'Computation Sheet'!D11*'Computation Sheet'!E11 -> 14806 | J10: 7000 | K10: =IF(H10="Yes",MAX(I10,J10)*8.33%,0) -> 1233.3398
B11: 7 | C11: D49415 | D11: Devesh Yadav | E11: Delhi | F11: Semi-Skilled | G11: =+VLOOKUP(C11,'Computation Sheet'!B11:L21,11,0) -> 53429 | H11: =IF(G11<=21000,"Yes","No") -> No | I11: =VLOOKUP(F11,$B$18:$H$23,7,0)/'Computation Sheet'!D12*'Computation Sheet'!E12 -> 16284 | J11: 7000 | K11: =IF(H11="Yes",MAX(I11,J11)*8.33%,0) -> 0
B12: 8 | C12: D49416 | D12: Dinesh Kumar | E12: Delhi | F12: Unskilled | G12: =+VLOOKUP(C12,'Computation Sheet'!B12:L22,11,0) -> 46720 | H12: =IF(G12<=21000,"Yes","No") -> No | I12: =VLOOKUP(F12,$B$18:$H$23,7,0)/'Computation Sheet'!D13*'Computation Sheet'!E13 -> 14806 | J12: 7000 | K12: =IF(H12="Yes",MAX(I12,J12)*8.33%,0) -> 0
B13: 9 | C13: D49418 | D13: Dushyant Yadav | E13: Delhi | F13: Unskilled | G13: =+VLOOKUP(C13,'Computation Sheet'!B13:L23,11,0) -> 54087 | H13: =IF(G13<=21000,"Yes","No") -> No | I13: =VLOOKUP(F13,$B$18:$H$23,7,0)/'Computation Sheet'!D14*'Computation Sheet'!E14 -> 14806 | J13: 7000 | K13: =IF(H13="Yes",MAX(I13,J13)*8.33%,0) -> 0
B14: 10 | C14: D49421 | D14: Indrajit Das | E14: Delhi | F14: Unskilled | G14: =+VLOOKUP(C14,'Computation Sheet'!B14:L24,11,0) -> 60000 | H14: =IF(G14<=21000,"Yes","No") -> No | I14: =VLOOKUP(F14,$B$18:$H$23,7,0)/'Computation Sheet'!D15*'Computation Sheet'!E15 -> 14806 | J14: 7000 | K14: =IF(H14="Yes",MAX(I14,J14)*8.33%,0) -> 0
B17: Nature | F17: Basic per month | G17: VDA per month | H17: Total per month | I17: Total per day
B18: Unskilled | F18: 14468 | G18: 338 | H18: 14806 | I18: 569
B19: Semi-skilled | F19: 15920 | G19: 364 | H19: 16284 | I19: 626
B20: Skilled | F20: 17508 | G20: 416 | H20: 17924 | I20: 689
B21: Clerical and supervisory staff - Non Matriculate | F21: 15920 | G21: 364 | H21: 16284 | I21: 626
B22: Clerical and supervisory staff - Matriculate but not Graduate | F22: 17508 | G22: 416 | H22: 17924 | I22: 689
B23: Clerical and supervisory staff - Graduate and above | F23: 19060 | G23: 462 | H23: 19522 | I23: 751

Sheet TDS
B5: Employee Info
B6: E Code | C6: PAN | D6: Name | E6: TDS
B9: D49404 | C9: AGOPR8914B | D9: Argha Roy | E9: 0
B10: D49405 | C10: AGOPR8914C | D10: Ashish Tiwari | E10: 0
B11: D49408 | C11: AGOPR8914D | D11: Aslam Sabri | E11: 1800
B12: D49409 | C12: AGOPR8914E | D12: Avik Das | E12: 0
B13: D49410 | C13: AGOPR8914F | D13: Avtar Singh | E13: 0
B14: D49411 | C14: AGOPR8914G | D14: Brotin Ghosh | E14: 0
B15: D49415 | C15: AGOPR8914H | D15: Devesh Yadav | E15: 1200
B16: D49416 | C16: AGOPR8914I | D16: Dinesh Kumar | E16: 600
B17: D49418 | C17: AGOPR8914J | D17: Dushyant Yadav | E17: 1250
B18: D49421 | C18: AGOPR8914K | D18: Indrajit Das | E18: 1400

Sheet Structure
A2: Sr.No | B2: E-Code | C2: Name | D2: Basic | E2: HRA | F2: Special All | G2: Total | H2: Increment | I2: Incrememt Rate | J2: Remark
A3: 1 | B3: D49404 | C3: Argha Roy | D3: 14300 | E3: 7104 | F3: 0 | G3: =ROUND(SUM(D3:F3),0) -> 21404 | H3: 1.June.2020 | I3: NA
A4: 2 | B4: D49405 | C4: Ashish Tiwari | D4: 17000 | E4: 8500 | F4: 5633 | G4: =ROUND(SUM(D4:F4),0) -> 31133 | H4: 1.June.2020 | I4: NA
A5: 3 | B5: D49408 | C5: Aslam Sabri | D5: 80000 | E5: 37000 | F5: 57075 | G5: =ROUND(SUM(D5:F5),0) -> 174075 | H5: 1.April.2020 | I5: 0.1
A6: 4 | B6: D49409 | C6: Avik Das | D6: 13500 | E6: 6284 | F6: 0 | G6: =ROUND(SUM(D6:F6),0) -> 19784 | H6: 1.June.2020 | I6: NA
A7: 5 | B7: D49410 | C7: Avtar Singh | D7: 13500 | E7: 6284 | F7: 0 | G7: =ROUND(SUM(D7:F7),0) -> 19784 | H7: 1.June.2020 | I7: NA
A8: 6 | B8: D49411 | C8: Brotin Ghosh | D8: 13500 | E8: 6284 | F8: 0 | G8: =ROUND(SUM(D8:F8),0) -> 19784 | H8: 1.June.2020 | I8: NA
A9: 7 | B9: D49415 | C9: Devesh Yadav | D9: 25000 | E9: 12500 | F9: 15929 | G9: =ROUND(SUM(D9:F9),0) -> 53429 | H9: 1.April.2020 | I9: 0.15
A10: 8 | B10: D49416 | C10: Dinesh Kumar | D10: 26000 | E10: 13000 | F10: 7720 | G10: =ROUND(SUM(D10:F10),0) -> 46720 | H10: 1.June.2020 | I10: NA
A11: 9 | B11: D49418 | C11: Dushyant Yadav | D11: 35000 | E11: 17500 | F11: 1587 | G11: =ROUND(SUM(D11:F11),0) -> 54087 | H11: 1.June.2020 | I11: NA
A12: 10 | B12: D49421 | C12: Indrajit Das | D12: 32000 | E12: 16000 | F12: 12000 | G12: =ROUND(SUM(D12:F12),0) -> 60000 | H12: 1.June.2020 | I12: NA
